odoo8_addon_survey_one_choice_per_column-8.0.1.0.0.99.dev14-py2.7-nspkg.pth
odoo8_addon_survey_one_choice_per_column-8.0.1.0.0.99.dev14.dist-info/METADATA
odoo8_addon_survey_one_choice_per_column-8.0.1.0.0.99.dev14.dist-info/RECORD
odoo8_addon_survey_one_choice_per_column-8.0.1.0.0.99.dev14.dist-info/WHEEL
odoo8_addon_survey_one_choice_per_column-8.0.1.0.0.99.dev14.dist-info/namespace_packages.txt
odoo8_addon_survey_one_choice_per_column-8.0.1.0.0.99.dev14.dist-info/top_level.txt
odoo_addons/survey_one_choice_per_column/README.rst
odoo_addons/survey_one_choice_per_column/__init__.py
odoo_addons/survey_one_choice_per_column/__openerp__.py
odoo_addons/survey_one_choice_per_column/i18n/de.po
odoo_addons/survey_one_choice_per_column/i18n/es.po
odoo_addons/survey_one_choice_per_column/i18n/fr.po
odoo_addons/survey_one_choice_per_column/i18n/hr.po
odoo_addons/survey_one_choice_per_column/i18n/pt_BR.po
odoo_addons/survey_one_choice_per_column/i18n/sl.po
odoo_addons/survey_one_choice_per_column/i18n/survey_one_choice_per_column.pot
odoo_addons/survey_one_choice_per_column/models/__init__.py
odoo_addons/survey_one_choice_per_column/models/survey_question.py
odoo_addons/survey_one_choice_per_column/models/survey_user_input_line.py
odoo_addons/survey_one_choice_per_column/static/description/icon.png
odoo_addons/survey_one_choice_per_column/static/src/js/survey_one_choice_per_column.js
odoo_addons/survey_one_choice_per_column/tests/__init__.py
odoo_addons/survey_one_choice_per_column/tests/test_survey_one_choice_per_column.py
odoo_addons/survey_one_choice_per_column/views/assets.xml
odoo_addons/survey_one_choice_per_column/views/survey_one_choice_per_column_templates.xml
